fdray/__init__.py
fdray/core/__init__.py
fdray/core/base.py
fdray/core/camera.py
fdray/core/color.py
fdray/core/light_source.py
fdray/core/media.py
fdray/core/object.py
fdray/core/renderer.py
fdray/core/scene.py
fdray/core/texture.py
fdray/data/__init__.py
fdray/data/color.py
fdray/data/field.py
fdray/data/frame.py
fdray/py.typed
fdray/typing.py
fdray/utils/__init__.py
fdray/utils/format.py
fdray/utils/image.py
fdray/utils/string.py
fdray/utils/vector.py
fdray-0.1.16.dist-info/WHEEL
fdray-0.1.16.dist-info/METADATA
fdray-0.1.16.dist-info/RECORD
