Metadata-Version: 2.3
Name: fdray
Version: 0.1.16
Summary: A Python interface for POV-Ray (Persistence of Vision Raytracer)
Keywords: povray,ray-tracing,3d,rendering,pov-ray,graphics
Author: daizutabi
Author-email: daizutabi <daizutabi@gmail.com>
License: MIT License
Classifier: Development Status :: 4 - Beta
Classifier: Intended Audience :: Developers
Classifier: Intended Audience :: Science/Research
Classifier: Topic :: Multimedia :: Graphics :: 3D Rendering
Classifier: Topic :: Scientific/Engineering :: Visualization
Classifier: Programming Language :: Python
Classifier: Programming Language :: Python :: 3.11
Classifier: Programming Language :: Python :: 3.12
Classifier: Programming Language :: Python :: 3.13
Classifier: Programming Language :: Python :: 3.14
Requires-Dist: numpy>=2
Requires-Dist: pillow>=10
Requires-Python: >=3.11
Project-URL: Documentation, https://daizutabi.github.io/fdray/
Project-URL: Issues, https://github.com/daizutabi/fdray/issues
Project-URL: Source, https://github.com/daizutabi/fdray
